databuilder/__init__.py
databuilder/callback/__init__.py
databuilder/callback/call_back.py
databuilder/extractor/__init__.py
databuilder/extractor/athena_metadata_extractor.py
databuilder/extractor/base_bigquery_extractor.py
databuilder/extractor/base_extractor.py
databuilder/extractor/bigquery_metadata_extractor.py
databuilder/extractor/bigquery_usage_extractor.py
databuilder/extractor/bigquery_watermark_extractor.py
databuilder/extractor/cassandra_extractor.py
databuilder/extractor/csv_extractor.py
databuilder/extractor/db2_metadata_extractor.py
databuilder/extractor/db_api_extractor.py
databuilder/extractor/druid_metadata_extractor.py
databuilder/extractor/generic_extractor.py
databuilder/extractor/glue_extractor.py
databuilder/extractor/hive_table_last_updated_extractor.py
databuilder/extractor/hive_table_metadata_extractor.py
databuilder/extractor/kafka_source_extractor.py
databuilder/extractor/mssql_metadata_extractor.py
databuilder/extractor/mysql_metadata_extractor.py
databuilder/extractor/neo4j_es_last_updated_extractor.py
databuilder/extractor/neo4j_extractor.py
databuilder/extractor/neo4j_search_data_extractor.py
databuilder/extractor/postgres_metadata_extractor.py
databuilder/extractor/presto_view_metadata_extractor.py
databuilder/extractor/snowflake_metadata_extractor.py
databuilder/extractor/sparksql_table_metadata_extractor.py
databuilder/extractor/sql_alchemy_extractor.py
databuilder/extractor/dashboard/__init__.py
databuilder/extractor/dashboard/mode_analytics/__init__.py
databuilder/extractor/dashboard/mode_analytics/mode_dashboard_charts_extractor.py
databuilder/extractor/dashboard/mode_analytics/mode_dashboard_constants.py
databuilder/extractor/dashboard/mode_analytics/mode_dashboard_executions_extractor.py
databuilder/extractor/dashboard/mode_analytics/mode_dashboard_extractor.py
databuilder/extractor/dashboard/mode_analytics/mode_dashboard_last_modified_timestamp_extractor.py
amundsen_databuilder_azure-2.6.5.dist-info/LICENSE
amundsen_databuilder_azure-2.6.5.dist-info/METADATA
amundsen_databuilder_azure-2.6.5.dist-info/NOTICE
amundsen_databuilder_azure-2.6.5.dist-info/WHEEL
amundsen_databuilder_azure-2.6.5.dist-info/top_level.txt
amundsen_databuilder_azure-2.6.5.dist-info/RECORD
